xai_feature_selection_new/__init__.py
xai_feature_selection_new/feature_selection.py
xai_feature_selection_new-0.2.dist-info/LICENSE.txt
xai_feature_selection_new-0.2.dist-info/METADATA
xai_feature_selection_new-0.2.dist-info/WHEEL
xai_feature_selection_new-0.2.dist-info/top_level.txt
xai_feature_selection_new-0.2.dist-info/RECORD
