Metadata-Version: 2.1
Name: xai-feature-selection-new
Version: 0.2
Summary: Feature selection using XAI
Home-page: UNKNOWN
Author: Yaganteeswarudu Akkem
Author-email: yaganteeswaritexpert@gmail.com
License: UNKNOWN
Keywords: machine learning,feature selection,explainable artificial intelligence,XAI
Platform: UNKNOWN
Classifier: Development Status :: 1 - Planning
Classifier: Intended Audience :: Developers
Classifier: Programming Language :: Python :: 3
Classifier: Operating System :: Unix
Classifier: Operating System :: MacOS :: MacOS X
Classifier: Operating System :: Microsoft :: Windows
License-File: LICENSE.txt
Requires-Dist: pandas ==2.0.*
Requires-Dist: lime
Requires-Dist: shap
